{
  "timestamp": "2026-04-05T15:33:41.982323Z",
  "paper_balance": 6.61,
  "current_price": 67493.51,
  "bull_prob": 1.981775,
  "bear_prob": 0.085189,
  "long_active": false,
  "long_entry": 0.0,
  "long_bars": 0,
  "long_size": 0.0,
  "short_active": false,
  "short_entry": 0.0,
  "short_bars": 0,
  "short_size": 0.0,
  "in_trade": false,
  "trade_type": null,
  "entry_price": 0.0,
  "bars_held": 0,
  "open_pnl_pct": 0.0,
  "open_pnl_usd": 0.0,
  "take_profit_target": 0.0,
  "stop_loss_target": 0.0,
  "trade_amount_btc": 0.0,
  "trade_amount_usd": 0.0
}